AUTHOR
COPYING
LICENSE
MANIFEST.in
README.rst
URL
VERSION
distribute_setup.py
setup.py
argparse/__init__.py
argparse.extra.egg-info/PKG-INFO
argparse.extra.egg-info/SOURCES.txt
argparse.extra.egg-info/dependency_links.txt
argparse.extra.egg-info/namespace_packages.txt
argparse.extra.egg-info/top_level.txt
argparse.extra.egg-info/zip-safe
argparse/extra/__init__.py
argparse/extra/parsers.py
docs/Makefile
docs/conf.py
docs/index.rst
docs/make.bat
docs/_build/doctrees/environment.pickle
docs/_build/doctrees/index.doctree
docs/_build/html/.buildinfo
docs/_build/html/genindex.html
docs/_build/html/index.html
docs/_build/html/objects.inv
docs/_build/html/search.html
docs/_build/html/searchindex.js
docs/_build/html/_sources/index.txt
docs/_build/html/_static/basic.css
docs/_build/html/_static/default.css
docs/_build/html/_static/doctools.js
docs/_build/html/_static/file.png
docs/_build/html/_static/jquery.js
docs/_build/html/_static/minus.png
docs/_build/html/_static/plus.png
docs/_build/html/_static/pygments.css
docs/_build/html/_static/searchtools.js
docs/_build/html/_static/sidebar.js
docs/_build/html/_static/underscore.js
example/sample_cli.py
tests/__init__.py