Metadata-Version: 1.0
Name: argparse.extra
Version: 0.0.2
Summary: Additional classes for argparse
Home-page: http://github.com/denz/argparse.extra
Author: Denis Mishchishin
Author-email: dennz78@gmail.com
License: Copyright (c) 2011, Denis Mishchishin
